iaar_scrapy_redis_sentinel/__init__.py
iaar_scrapy_redis_sentinel/bloomfilter.py
iaar_scrapy_redis_sentinel/connection.py
iaar_scrapy_redis_sentinel/defaults.py
iaar_scrapy_redis_sentinel/dupefilter.py
iaar_scrapy_redis_sentinel/picklecompat.py
iaar_scrapy_redis_sentinel/pipelines.py
iaar_scrapy_redis_sentinel/queue.py
iaar_scrapy_redis_sentinel/scheduler.py
iaar_scrapy_redis_sentinel/spiders.py
iaar_scrapy_redis_sentinel/stats.py
iaar_scrapy_redis_sentinel/utils.py
iaar_scrapy_redis_sentinel-1.0.0.dist-info/LICENSE
iaar_scrapy_redis_sentinel-1.0.0.dist-info/METADATA
iaar_scrapy_redis_sentinel-1.0.0.dist-info/WHEEL
iaar_scrapy_redis_sentinel-1.0.0.dist-info/top_level.txt
iaar_scrapy_redis_sentinel-1.0.0.dist-info/zip-safe
iaar_scrapy_redis_sentinel-1.0.0.dist-info/RECORD
