Metadata-Version: 2.1
Name: iaar_scrapy_redis_sentinel
Version: 1.0.0
Summary: this is a class from scrapy
Home-page: https://github.com/pypa/sampleproject
Author: Gie
Author-email: 593443714@qq.com
License: MIT
Keywords: iaar utils
Classifier: License :: OSI Approved :: MIT License
Classifier: Programming Language :: Python
Classifier: Intended Audience :: Developers
Classifier: Operating System :: OS Independent
License-File: LICENSE
